ejabberd_extauth.py
ejabberd_extauth-1.0.1.dist-info/METADATA
ejabberd_extauth-1.0.1.dist-info/WHEEL
ejabberd_extauth-1.0.1.dist-info/RECORD
