Metadata-Version: 2.1
Name: ejabberd-extauth
Version: 1.0.1
Summary: Library for writing ejabberd external auth scripts in Python
Home-page: https://codeberg.org/Natureshadow/ejabberd-extauth
License: MIT
Keywords: ejabberd,xmpp
Author: Dominik George
Author-email: nik@naturalnet.de
Requires-Python: >=3.11,<4.0
Classifier: Intended Audience :: Developers
Classifier: License :: OSI Approved :: MIT License
Classifier: Programming Language :: Python :: 3
Classifier: Programming Language :: Python :: 3.11
Classifier: Programming Language :: Python :: 3.12
Classifier: Topic :: Communications :: Chat
Classifier: Topic :: Internet :: XMPP
Requires-Dist: pyyaml (>=6.0.1,<7.0.0)
Project-URL: Repository, https://codeberg.org/Natureshadow/ejabberd-extauth
